iam_watching/__init__.py
iam_watching/__main__.py
iam_watching/command_line.py
iam_watching-1.6.0.dist-info/METADATA
iam_watching-1.6.0.dist-info/WHEEL
iam_watching-1.6.0.dist-info/entry_points.txt
iam_watching-1.6.0.dist-info/RECORD
