Metadata-Version: 2.3
Name: iam_watching
Version: 1.6.0
Summary: Realtime monitor for IAM activity for IaC projects
License: MIT
Author: Dank
Author-email: 4129589+danktec@users.noreply.github.com
Requires-Python: >=3.13,<4.0
Classifier: License :: OSI Approved :: MIT License
Classifier: Programming Language :: Python :: 3
Classifier: Programming Language :: Python :: 3.13
Requires-Dist: boto3 (>=1.40.8,<2.0.0)
Requires-Dist: datetime (>=5.5,<6.0)
Requires-Dist: flake8 (>=7.3.0,<8.0.0)
Requires-Dist: taskipy (>=1.14.1,<2.0.0)
